setup.py
aint/__init__.py
aint.egg-info/PKG-INFO
aint.egg-info/SOURCES.txt
aint.egg-info/dependency_links.txt
aint.egg-info/top_level.txt