Metadata-Version: 2.1
Name: aint
Version: 0.0.1
Summary: aint
Home-page: UNKNOWN
Author: Anish Agrawal
Author-email: your.email@example.com
License: UNKNOWN
Platform: UNKNOWN
